LiteSQL
