Metadata-Version: 2.1
Name: LiteSQL
Version: 2.0.1
Summary: Библиотека для легкого использования БД!
Home-page: UNKNOWN
Author-email: ma_mush@mail.ru
License: UNKNOWN
Platform: UNKNOWN
Requires-Python: >=3.6
